<?xml version="1.0" encoding="UTF-8"?>
<objects serializationModel="Studio.02.03.00">
	<object class="ParameterPreset" id="{b07033d1-9cd7-42a3-98fc-57835bd0e475}">
		<property name="name">
			<value>music</value>
		</property>
		<relationship name="folder">
			<destination>{485d4093-dfeb-4df5-9499-361517afd502}</destination>
		</relationship>
		<relationship name="parameter">
			<destination>{e318905e-b720-45da-bfc6-d3a1e8a69b3f}</destination>
		</relationship>
	</object>
	<object class="GameParameter" id="{e318905e-b720-45da-bfc6-d3a1e8a69b3f}">
		<property name="parameterType">
			<value>2</value>
		</property>
		<property name="maximum">
			<value>3</value>
		</property>
		<property name="enumerationLabels">
			<value>normal</value>
			<value>animals</value>
			<value>enemies</value>
		</property>
		<property name="initialValue">
			<value>0</value>
		</property>
	</object>
</objects>
