<?xml version="1.0" encoding="UTF-8"?>
<objects serializationModel="Studio.02.03.00">
	<object class="AudioFile" id="{0eb856dc-2073-42d9-8fa2-2705019443ee}">
		<property name="assetPath">
			<value>sfx/upgrade/upgrade_plastic_5.ogg</value>
		</property>
		<property name="frequencyInKHz">
			<value>48</value>
		</property>
		<property name="channelCount">
			<value>1</value>
		</property>
		<property name="length">
			<value>0.66200000000000003</value>
		</property>
		<relationship name="masterAssetFolder">
			<destination>{525b0427-f18d-4eb4-828e-2ad3682f9cfd}</destination>
		</relationship>
	</object>
</objects>
